{
  "allLanguages": ["en", "fr"],
  "defaultLanguage": "en",
  "currentPagesDir": "src/pages_",
  "finalPagesDir": "src/pages",
  "localesPath": "public/locales",
  "pages": {
    "*": ["shared", "form"],
    "/": [
      "udiniHeader",
      "udiniFooter",
      "udiniHome",
      "udiniSharedCommunitySection",
      "udiniHomeV2",
      "udiniAbout"
    ],
    "/products": [
      "udiniProducts",
      "udiniPix",
      "udiniHeader",
      "udiniFooter",
      "udiniSharedCommunitySection",
      "udiniHome",
      "pixSignup",
      "udiniSmile",
      "udiniHeader",
      "udiniFooter",
      "udiniSharedCommunitySection",
      "udiniHomeV2"
    ],
    "/about": ["udiniHeader", "udiniFooter", "udiniAbout", "udiniSharedCommunitySection"],
    "/community": ["udiniHeader", "udiniFooter", "udiniCommunity", "udiniSharedCommunitySection"],
    "/contact": ["udiniHeader", "udiniFooter", "udiniContact"],
    "/faq": ["udiniHeader", "udiniFooter", "udiniFaq"],
    "/terms-and-conditions": ["udiniHeader", "udiniFooter", "udiniTermsAndConditions"],
    "/terms-of-use": ["udiniHeader", "udiniFooter", "udiniTermsOfUse"],
    "/form/community": ["udiniCommunity", "udiniSmile"],
    "/form/smile": ["udiniCommunity", "udiniSmile"],
    "/form/[mode]/[stage]": [
      "udiniHeader",
      "udiniFooter",
      "udiniSharedCommunitySection",
      "udiniSmile",
      "udiniCommunity"
    ],
    "/products/pix": [
      "udiniPix",
      "udiniHeader",
      "udiniFooter",
      "udiniSharedCommunitySection",
      "udiniHome",
      "pixSignup"
    ],
    "/products/smile": ["udiniSmile", "udiniHeader", "udiniFooter", "udiniSharedCommunitySection"],
    "/pix": [
      "pixCenteredBlock",
      "pixSignIn",
      "pixForgotPassword",
      "profile",
      "pixFunnel",
      "pixCustomizationParameters",
      "pixSignup",
      "pixHome",
      "pixSidebar",
      "pixSettingsPhotos",
      "pixLanguage",
      "pixProfileHome",
      "pixProfilePhotoBar",
      "signup",
      "pixSubscription",
      "pixPayment",
      "pixInvoices",
      "pixImport"
    ],
    "/pix/signin": ["pixCenteredBlock", "pixSignIn"],
    "/pix/signup": [
      "signup",
      "pixCenteredBlock",
      "pixSignIn",
      "pixForgotPassword",
      "profile",
      "pixFunnel",
      "pixCustomizationParameters",
      "pixSignup",
      "pixHome",
      "pixSidebar",
      "pixSettingsPhotos",
      "pixLanguage"
    ],
    "/pix/photo-import": ["pixImport", "pixEditor", "pixProfilePhotoBar"],
    "/pix/funnel": ["signup", "pixCenteredBlock", "pixFunnel", "pixCustomizationParameters"],
    "/pix/password-forgotten": ["pixCenteredBlock", "pixForgotPassword"],
    "/pix/restore": ["pixResetPassword"]
  }
}
